simpleTR64-1.0.6.data/scripts/upnp_tools
simpleTR64-1.0.6.dist-info/DESCRIPTION.rst
simpleTR64-1.0.6.dist-info/METADATA
simpleTR64-1.0.6.dist-info/RECORD
simpleTR64-1.0.6.dist-info/WHEEL
simpleTR64-1.0.6.dist-info/metadata.json
simpleTR64-1.0.6.dist-info/top_level.txt
simpletr64/__init__.py
simpletr64/devicetr64.py
simpletr64/discover.py
simpletr64/actions/__init__.py
simpletr64/actions/fritz.py
simpletr64/actions/lan.py
simpletr64/actions/system.py
simpletr64/actions/wan.py
simpletr64/actions/wifi.py
simpletr64/tools/__init__.py
simpletr64/tools/execute_action.py
simpletr64/tools/gather_device_upnp_info.py
simpletr64/tools/run_discovery_upnp_tr64.py
tests/__init__.py
tests/context.py
tests/defaults.py
tests/test_device.py
tests/test_discover.py
tests/test_dlna.py
tests/test_fritz.py
tests/test_lan.py
tests/test_system.py
tests/test_wan.py
tests/test_wifi.py
