Metadata-Version: 2.0
Name: simpleTR64
Version: 1.0.6
Summary: An easy to use UPnP TR64 protocol library
Home-page: http://bpannier.github.io/simpletr64/
Author: Benjamin Pannier
Author-email: sourcecode@ka.ro
License: Apache 2.0
Keywords: TR64 protocol network UPnP
Platform: UNKNOWN
Classifier: Development Status :: 4 - Beta
Classifier: Intended Audience :: Developers
Classifier: Intended Audience :: Education
Classifier: Intended Audience :: System Administrators
Classifier: Intended Audience :: Telecommunications Industry
Classifier: License :: OSI Approved :: Apache Software License
Classifier: Programming Language :: Python :: 2
Classifier: Programming Language :: Python :: 2.6
Classifier: Programming Language :: Python :: 2.7
Classifier: Programming Language :: Python :: 3
Classifier: Programming Language :: Python :: 3.2
Classifier: Programming Language :: Python :: 3.3
Classifier: Programming Language :: Python :: 3.4
Classifier: Programming Language :: Python :: 3.5
Classifier: Topic :: Home Automation
Classifier: Topic :: System :: Networking
Classifier: Topic :: System :: Networking :: Monitoring
Classifier: Topic :: Software Development :: Libraries
Requires-Dist: requests
